printfx/__init__.py
printfx/base.py
printfx/colors.py
printfx/fontsize.py
printfxpy-1.1.0.dist-info/licenses/LICENSE
printfxpy-1.1.0.dist-info/METADATA
printfxpy-1.1.0.dist-info/WHEEL
printfxpy-1.1.0.dist-info/top_level.txt
printfxpy-1.1.0.dist-info/RECORD
